[
  {
    "Owner": {
      "$id": "1",
      "Account": {
        "$id": "2",
        "Owner": null,
        "Balance": 0.0,
        "Credit": 0.0
      },
      "FirstName": "Mladen",
      "LastName": "Milosevic"
    },
    "Balance": 0.0,
    "Credit": 0.0
  },
  {
    "Owner": {
      "$id": "3",
      "Account": {
        "$id": "4",
        "Owner": {
          "$ref": "3"
        },
        "Balance": 0.0,
        "Credit": 0.0
      },
      "FirstName": "Mladen",
      "LastName": "Milosevic"
    },
    "Balance": 0.0,
    "Credit": 0.0
  }
]